pymox_tools1/__init__.py
pymox_tools1/commits_semantic.md
pymox_tools1/compare_keys.py
pymox_tools1/convert_readme.py
pymox_tools1/greetings.py
pymox_tools1/tokens.py
pymox_tools1-1.0.6.dist-info/METADATA
pymox_tools1-1.0.6.dist-info/WHEEL
pymox_tools1-1.0.6.dist-info/top_level.txt
pymox_tools1-1.0.6.dist-info/RECORD
